disaggregator/__init__.py
disaggregator/methods.py
disaggregator/preprocessors.py
data_decomposition_platform-0.0.1.dist-info/LICENSE
data_decomposition_platform-0.0.1.dist-info/METADATA
data_decomposition_platform-0.0.1.dist-info/WHEEL
data_decomposition_platform-0.0.1.dist-info/top_level.txt
data_decomposition_platform-0.0.1.dist-info/RECORD
