Metadata-Version: 2.1
Name: data-decomposition-platform
Version: 0.0.1
Summary: Data Decomposition Platform library for data disaggregation.
Home-page: https://github.com/google-marketing-solutions/data_decomposition_platform
Author: Google gTech Ads EMEA Privacy Data Science Team
License: Apache 2.0
Keywords: 1pd privacy AI ML aggregated data
Classifier: Intended Audience :: Developers
Classifier: Intended Audience :: Science/Research
Classifier: License :: OSI Approved :: Apache Software License
Classifier: Topic :: Scientific/Engineering :: Artificial Intelligence
Requires-Python: >=3.10
License-File: LICENSE
Requires-Dist: jax ==0.4.21
Requires-Dist: numpy ==1.26.2
Requires-Dist: numpyro ==0.13.2
Requires-Dist: pandas ==2.1.3
Requires-Dist: tensorflow ==2.15.0
